[
    {
        "titulo": "Assista aos telejornais da TV Subaé",
        "resumo": "Atualização via Radar Consuldente.",
        "cat": "FEIRA DE SANTANA",
        "fonte": "G1 Feira",
        "data": "19:24",
        "url": "https://g1.globo.com/ba/feira-de-santana-regiao/ao-vivo/assista-aos-telejornais-da-tv-subae.ghtml",
        "img": "https://picsum.photos/seed/296/800/400"
    },
    {
        "titulo": "Câmara de Feira de Santana aprova lei de garantia para investidores do Hospital Municipal ",
        "resumo": "Portal Oficial - Clique para ler mais.",
        "cat": "FEIRA DE SANTANA",
        "fonte": "Acorda Cidade",
        "data": "19:24",
        "url": "https://www.acordacidade.com.br/feira-de-santana/camara-de-feira-de-santana-aprova-lei-de-garantia-para-investidores-do-hospital-municipal/",
        "img": "https://picsum.photos/seed/344/800/400"
    },
    {
        "titulo": "Presidente do CRO-BA se reúne com a Comissão de Remidos",
        "resumo": "Atualização via Radar Consuldente.",
        "cat": "ODONTOLOGIA",
        "fonte": "CRO-BA",
        "data": "19:23",
        "url": "https://croba.org.br/presidente-do-cro-ba-se-reune-com-a-comissao-de-remidos/",
        "img": "https://picsum.photos/seed/467/800/400"
    },
    {
        "titulo": "ABO se torna  signatária do Manifesto ESG/ODS por Ambientes Sustentáveis, Saudáveis, Inteligent",
        "resumo": "Portal Oficial - Clique para ler mais.",
        "cat": "ODONTOLOGIA",
        "fonte": "ABO-BA",
        "data": "19:23",
        "url": "https://abo-ba.org.br/abo-se-torna-signataria-do-manifesto-esg-ods-por-ambientes-sustentaveis-saudaveis-inteligentes-e-felizes/",
        "img": "https://abo-ba.org.br/wp-content/uploads/2026/04/WhatsApp-Image-2026-04-23-at-09.02.46.jpeg"
    },
    {
        "titulo": "São João da ABO-BA celebra tradição, alegria e união da classe odontológica",
        "resumo": "Portal Oficial - Clique para ler mais.",
        "cat": "ODONTOLOGIA",
        "fonte": "ABO-BA",
        "data": "19:24",
        "url": "https://abo-ba.org.br/sao-joao-da-abo-ba-celebra-tradicao-alegria-e-uniao-da-classe-odontologica/",
        "img": "https://abo-ba.org.br/wp-content/uploads/2025/07/2.png"
    },
    {
        "titulo": "Vídeos do g1 e TV Subaé - quarta-feira, 29 de abril de 2026",
        "resumo": "Atualização via Radar Consuldente.",
        "cat": "FEIRA DE SANTANA",
        "fonte": "G1 Feira",
        "data": "19:24",
        "url": "https://g1.globo.com/ba/feira-de-santana-regiao/edicao/2026/04/29/videos-do-g1-e-tv-subae-quarta-feira-29-de-abril-de-2026.ghtml",
        "img": "https://picsum.photos/seed/727/800/400"
    },
    {
        "titulo": "Montanhista morre após cair de cerca de 80 metros durante escalada no interior da Bahia",
        "resumo": "Atualização via Radar Consuldente.",
        "cat": "FEIRA DE SANTANA",
        "fonte": "G1 Feira",
        "data": "19:24",
        "url": "https://g1.globo.com/ba/feira-de-santana-regiao/noticia/2026/04/29/montanhista-morre-apos-cair-de-cerca-de-80-metros-durante-escalada-no-interior-da-bahia.ghtml",
        "img": "https://picsum.photos/seed/900/800/400"
    },
    {
        "titulo": "Funcionária é flagrada tentando sair de supermercado com alimentos escondidos na mochila",
        "resumo": "Portal Oficial - Clique para ler mais.",
        "cat": "FEIRA DE SANTANA",
        "fonte": "Acorda Cidade",
        "data": "19:24",
        "url": "https://www.acordacidade.com.br/policia/funcionaria-e-flagrada-tentando-sair-de-supermercado-com-alimentos-escondidos-na-mochila/",
        "img": "https://picsum.photos/seed/638/800/400"
    },
    {
        "titulo": "Calcinha Preta e Toque Dez são confirmadas no São João de Coração de Maria",
        "resumo": "Portal Oficial - Clique para ler mais.",
        "cat": "FEIRA DE SANTANA",
        "fonte": "Acorda Cidade",
        "data": "19:24",
        "url": "https://www.acordacidade.com.br/sao-joao/calcinha-preta-e-toque-dez-sao-confirmadas-no-sao-joao-de-coracao-de-maria/",
        "img": "https://picsum.photos/seed/999/800/400"
    },
    {
        "titulo": "Campanha Vacinar é muito Brasil foca em viajantes para Copa",
        "resumo": "Portal Oficial - Clique para ler mais.",
        "cat": "FEIRA DE SANTANA",
        "fonte": "Folha do Estado",
        "data": "19:24",
        "url": "https://www.jornalfolhadoestado.com/saude/campanha-vacinar-e-muito-brasil-foca-em-viajantes-para-copa/",
        "img": "https://picsum.photos/seed/816/800/400"
    },
    {
        "titulo": "56% dos eleitores aprovam governo de Jerônimo Rodrigues, diz Quaest",
        "resumo": "Portal Oficial - Clique para ler mais.",
        "cat": "FEIRA DE SANTANA",
        "fonte": "Folha do Estado",
        "data": "19:24",
        "url": "https://www.jornalfolhadoestado.com/politica/56-dos-eleitores-aprovam-governo-de-jeronimo-rodrigues-diz-quaest/",
        "img": "https://picsum.photos/seed/411/800/400"
    },
    {
        "titulo": "Cirurgia Estética Orofacial é oficialmente regulamentada",
        "resumo": "Portal Oficial - Clique para ler mais.",
        "cat": "ODONTOLOGIA",
        "fonte": "CFO Federal",
        "data": "19:23",
        "url": "https://website.cfo.org.br/cirurgia-estetica-orofacial-e-oficialmente-regulamentada/",
        "img": "https://website.cfo.org.br/wp-content/uploads/2026/03/DSC0432-scaled.jpg"
    },
    {
        "titulo": "Projeto que prevê distribuição gratuita de Mounjaro em Feira de Santana é aprovado em primeira ",
        "resumo": "Atualização via Radar Consuldente.",
        "cat": "FEIRA DE SANTANA",
        "fonte": "G1 Feira",
        "data": "19:24",
        "url": "https://g1.globo.com/ba/feira-de-santana-regiao/noticia/2026/04/29/projeto-que-preve-distribuicao-gratuita-de-mounjaro-em-feira-de-santana-e-aprovado-em-primeira-votacao.ghtml",
        "img": "https://picsum.photos/seed/366/800/400"
    },
    {
        "titulo": "Rui Costa e Jaques Wagner lideram pesquisa para o Senado da Bahia",
        "resumo": "Portal Oficial - Clique para ler mais.",
        "cat": "FEIRA DE SANTANA",
        "fonte": "Folha do Estado",
        "data": "19:24",
        "url": "https://www.jornalfolhadoestado.com/politica/rui-costa-e-jaques-wagner-lideram-pesquisa-para-o-senado-da-bahia/",
        "img": "https://picsum.photos/seed/35/800/400"
    },
    {
        "titulo": "Mais de 1 milhão de famílias baianas ainda não recebem gratuidade na conta de luz; saiba como a",
        "resumo": "Portal Oficial - Clique para ler mais.",
        "cat": "FEIRA DE SANTANA",
        "fonte": "Acorda Cidade",
        "data": "19:24",
        "url": "https://www.acordacidade.com.br/bahia/mais-de-1-milhao-de-familias-baianas-ainda-nao-recebem-gratuidade-na-conta-de-luz-saiba-como-aderir/",
        "img": "https://picsum.photos/seed/319/800/400"
    },
    {
        "titulo": "CRO-BA acompanha, em Brasília, aprovação do relatório do PL 1365/2022 na CAE",
        "resumo": "Atualização via Radar Consuldente.",
        "cat": "ODONTOLOGIA",
        "fonte": "CRO-BA",
        "data": "19:23",
        "url": "https://croba.org.br/cro-ba-acompanha-em-brasilia-aprovacao-do-relatorio-do-pl-1365-2022-na-cae/",
        "img": "https://picsum.photos/seed/936/800/400"
    },
    {
        "titulo": "Prefeitura de Conceição do Jacuípe convoca aprovados em processo seletivo; veja lista completa",
        "resumo": "Portal Oficial - Clique para ler mais.",
        "cat": "FEIRA DE SANTANA",
        "fonte": "Acorda Cidade",
        "data": "19:24",
        "url": "https://www.acordacidade.com.br/empregos/concursos/prefeitura-de-conceicao-do-jacuipe-convoca-aprovados-em-processo-seletivo-veja-lista-completa/",
        "img": "https://picsum.photos/seed/433/800/400"
    },
    {
        "titulo": "Suspeito de integrar esquema de locação de veículos fraudulenta é preso na BA; prejuízo ultrapa",
        "resumo": "Atualização via Radar Consuldente.",
        "cat": "FEIRA DE SANTANA",
        "fonte": "G1 Feira",
        "data": "19:24",
        "url": "https://g1.globo.com/ba/feira-de-santana-regiao/noticia/2026/04/29/suspeito-de-integrar-esquema-de-locacao-de-veiculos-fraudulenta-e-preso-na-ba.ghtml",
        "img": "https://picsum.photos/seed/899/800/400"
    },
    {
        "titulo": "Mais de 125 km de rodovias estaduais devem ser pavimentados na Bahia; confira as licitações em ",
        "resumo": "Portal Oficial - Clique para ler mais.",
        "cat": "FEIRA DE SANTANA",
        "fonte": "Acorda Cidade",
        "data": "19:24",
        "url": "https://www.acordacidade.com.br/bahia/mais-de-125-km-de-rodovias-estaduais-devem-ser-pavimentados-na-bahia-confira-as-licitacoes-em-andamento/",
        "img": "https://picsum.photos/seed/314/800/400"
    },
    {
        "titulo": "Daniela Mercury pede desculpas após acusar Edson Gomes de violência doméstica",
        "resumo": "Portal Oficial - Clique para ler mais.",
        "cat": "FEIRA DE SANTANA",
        "fonte": "Folha do Estado",
        "data": "19:24",
        "url": "https://www.jornalfolhadoestado.com/famosos/daniela-mercury-pede-desculpas-apos-acusar-edson-gomes-de-violencia-domestica/",
        "img": "https://picsum.photos/seed/598/800/400"
    },
    {
        "titulo": "A nova era da harmonização orofacial começa com conhecimento de verdade e você pode fazer parte",
        "resumo": "Portal Oficial - Clique para ler mais.",
        "cat": "ODONTOLOGIA",
        "fonte": "ABO-BA",
        "data": "19:24",
        "url": "https://abo-ba.org.br/a-nova-era-da-harmonizacao-orofacial-comeca-com-conhecimento-de-verdade-e-voce-pode-fazer-parte/",
        "img": "https://abo-ba.org.br/wp-content/uploads/2025/05/Black-and-Gold-Illustrated-Webinar-Event-Instagram-Post-1920-x-1080-px.png"
    },
    {
        "titulo": "Presidente do CFO prestigia posse da nova diretoria do CRO-GO",
        "resumo": "Portal Oficial - Clique para ler mais.",
        "cat": "ODONTOLOGIA",
        "fonte": "CFO Federal",
        "data": "19:23",
        "url": "https://website.cfo.org.br/presidente-do-cfo-prestigia-posse-da-nova-diretoria-do-cro-go/",
        "img": "https://website.cfo.org.br/wp-content/uploads/2026/03/CAR08361-scaled.jpg"
    },
    {
        "titulo": "CRO-BA participa de reunião com gestão municipal de Ipiaú em defesa da valorização da Odontolog",
        "resumo": "Atualização via Radar Consuldente.",
        "cat": "ODONTOLOGIA",
        "fonte": "CRO-BA",
        "data": "19:23",
        "url": "https://croba.org.br/cro-ba-participa-de-reuniao-com-gestao-municipal-de-ipiau-em-defesa-da-valorizacao-da-odontologia/",
        "img": "https://picsum.photos/seed/617/800/400"
    },
    {
        "titulo": "ABO Bahia sedia Jornada Estadual sobre Hanseníase: “Conhecer e Cuidar, de Janeiro a Janeiro”",
        "resumo": "Portal Oficial - Clique para ler mais.",
        "cat": "ODONTOLOGIA",
        "fonte": "ABO-BA",
        "data": "19:24",
        "url": "https://abo-ba.org.br/abo-bahia-sedia-jornada-estadual-sobre-hanseniase-conhecer-e-cuidar-de-janeiro-a-janeiro/",
        "img": "https://abo-ba.org.br/wp-content/uploads/2025/05/capas-abo-.png"
    },
    {
        "titulo": "Professor de jiu-jitsu Melqui Galvão é preso sob suspeita de abuso sexual contra alunas",
        "resumo": "Portal Oficial - Clique para ler mais.",
        "cat": "FEIRA DE SANTANA",
        "fonte": "Folha do Estado",
        "data": "19:24",
        "url": "https://www.jornalfolhadoestado.com/esportes/professor-de-jiu-jitsu-melqui-galvao-e-preso-sob-suspeita-de-abuso-sexual-contra-alunas/",
        "img": "https://picsum.photos/seed/665/800/400"
    },
    {
        "titulo": "Manual e anexos",
        "resumo": "Portal Oficial - Clique para ler mais.",
        "cat": "ODONTOLOGIA",
        "fonte": "CFO Federal",
        "data": "19:23",
        "url": "https://website.cfo.org.br/modelos-de-prontuarios",
        "img": "https://website.cfo.org.br/wp-content/uploads/2026/03/Manual-do-Prontuario-1-scaled.png"
    },
    {
        "titulo": "CRO-BA participa de ato público em Brasília em defesa da PEC 2/2026 e dialoga com o senador Ang",
        "resumo": "Atualização via Radar Consuldente.",
        "cat": "ODONTOLOGIA",
        "fonte": "CRO-BA",
        "data": "19:23",
        "url": "https://croba.org.br/cro-ba-participa-de-ato-publico-em-brasilia-em-defesa-da-pec-2-2026-e-dialoga-com-o-senador-angelo-coronel/",
        "img": "https://picsum.photos/seed/634/800/400"
    },
    {
        "titulo": "Clube de Benefícios",
        "resumo": "Portal Oficial - Clique para ler mais.",
        "cat": "ODONTOLOGIA",
        "fonte": "CFO Federal",
        "data": "19:23",
        "url": "https://website.cfo.org.br/clube-beneficios",
        "img": "https://website.cfo.org.br/wp-content/uploads/2026/03/arte-beneficios-scaled.png"
    },
    {
        "titulo": "Prefeitura divulga lista de aprovados em processo seletivo em Conceição do Jacuípe",
        "resumo": "Atualização via Radar Consuldente.",
        "cat": "FEIRA DE SANTANA",
        "fonte": "G1 Feira",
        "data": "19:24",
        "url": "https://g1.globo.com/ba/feira-de-santana-regiao/noticia/2026/04/29/processo-seletivo-bahia.ghtml",
        "img": "https://picsum.photos/seed/889/800/400"
    },
    {
        "titulo": "Receita Federal apreende mais de 620 toneladas de minérios no Porto de Salvador",
        "resumo": "Portal Oficial - Clique para ler mais.",
        "cat": "FEIRA DE SANTANA",
        "fonte": "Folha do Estado",
        "data": "19:24",
        "url": "https://www.jornalfolhadoestado.com/policia/receita-federal-apreende-mais-de-620-toneladas-de-minerios-no-porto-de-salvador/",
        "img": "https://picsum.photos/seed/248/800/400"
    },
    {
        "titulo": "Presidente do CFO prestigia posse da nova diretoria do CRO-DF",
        "resumo": "Portal Oficial - Clique para ler mais.",
        "cat": "ODONTOLOGIA",
        "fonte": "CFO Federal",
        "data": "19:23",
        "url": "https://website.cfo.org.br/presidente-do-cfo-prestigia-posse-da-nova-diretoria-do-cro-df/",
        "img": "https://website.cfo.org.br/wp-content/uploads/2026/03/DSCF3872-scaled.jpg"
    },
    {
        "titulo": "CRO-BA participa da 1ª cerimônia oficial de assinatura do Manifesto ESG / ODS",
        "resumo": "Atualização via Radar Consuldente.",
        "cat": "ODONTOLOGIA",
        "fonte": "CRO-BA",
        "data": "19:23",
        "url": "https://croba.org.br/cro-ba-participa-da-1a-cerimonia-oficial-de-assinatura-do-manifesto-esg-ods/",
        "img": "https://picsum.photos/seed/918/800/400"
    },
    {
        "titulo": "Circuito CRO-BA – Ética em Movimento reúne profissionais e estudantes em Senhor do Bonfim",
        "resumo": "Atualização via Radar Consuldente.",
        "cat": "ODONTOLOGIA",
        "fonte": "CRO-BA",
        "data": "19:23",
        "url": "https://croba.org.br/circuito-cro-ba-etica-em-movimento-reune-profissionais-e-estudantes-em-senhor-do-bonfim/",
        "img": "https://picsum.photos/seed/393/800/400"
    },
    {
        "titulo": "Café &#038; Prosa promove reflexão sobre autocuidado na ABO-BA",
        "resumo": "Portal Oficial - Clique para ler mais.",
        "cat": "ODONTOLOGIA",
        "fonte": "ABO-BA",
        "data": "19:24",
        "url": "https://abo-ba.org.br/cafe-prosa-promove-reflexao-sobre-autocuidado-na-abo-ba/",
        "img": "https://abo-ba.org.br/wp-content/uploads/2025/07/1.png"
    },
    {
        "titulo": "ODONTOLOGIA HOSPITALAR AVANÇA NO BRASIL COM MODELO INTEGRADOR E CONQUISTA NOVO PROTAGONISMO NAC",
        "resumo": "Portal Oficial - Clique para ler mais.",
        "cat": "ODONTOLOGIA",
        "fonte": "CFO Federal",
        "data": "19:23",
        "url": "https://website.cfo.org.br/odontologia-hospitalar-avanca-no-brasil-com-modelo-integrador-e-conquista-novo-protagonismo-nacional/",
        "img": "https://picsum.photos/seed/94/800/400"
    }
]