[
    {
        "titulo": "MC Ryan e MC Poze do Rodo teriam movimentado R$ 1,6 bilhão em esquema de rifas ilegais",
        "resumo": "Portal Oficial - Clique para ler mais.",
        "cat": "FEIRA DE SANTANA",
        "fonte": "Folha do Estado",
        "data": "19:14",
        "url": "https://www.jornalfolhadoestado.com/brasil/mc-ryan-e-mc-poze-do-rodo-teriam-movimentado-r-16-bilhao-em-esquema-de-rifas-ilegais/",
        "img": "https://picsum.photos/seed/592/800/400"
    },
    {
        "titulo": "Controle da dor no câncer avança com novas técnicas de anestesia",
        "resumo": "Portal Oficial - Clique para ler mais.",
        "cat": "FEIRA DE SANTANA",
        "fonte": "Acorda Cidade",
        "data": "19:14",
        "url": "https://www.acordacidade.com.br/saude/controle-da-dor-no-cancer-avanca-com-novas-tecnicas-de-anestesia/",
        "img": "https://picsum.photos/seed/367/800/400"
    },
    {
        "titulo": "Manual e anexos",
        "resumo": "Portal Oficial - Clique para ler mais.",
        "cat": "ODONTOLOGIA",
        "fonte": "CFO Federal",
        "data": "19:13",
        "url": "https://website.cfo.org.br/modelos-de-prontuarios",
        "img": "https://website.cfo.org.br/wp-content/uploads/2026/03/Manual-do-Prontuario-1-scaled.png"
    },
    {
        "titulo": "Goiano que desapareceu após sair para encontro é achado morto na Argentina",
        "resumo": "Portal Oficial - Clique para ler mais.",
        "cat": "FEIRA DE SANTANA",
        "fonte": "Folha do Estado",
        "data": "19:14",
        "url": "https://www.jornalfolhadoestado.com/brasil/goiano-que-desapareceu-apos-sair-para-encontro-e-achado-morto-na-argentina/",
        "img": "https://picsum.photos/seed/847/800/400"
    },
    {
        "titulo": "Presidente do CRO-BA se reúne com a Comissão de Remidos",
        "resumo": "Atualização via Radar Consuldente.",
        "cat": "ODONTOLOGIA",
        "fonte": "CRO-BA",
        "data": "19:14",
        "url": "https://croba.org.br/presidente-do-cro-ba-se-reune-com-a-comissao-de-remidos/",
        "img": "https://picsum.photos/seed/847/800/400"
    },
    {
        "titulo": "Mais de 1,5 mil caranguejos e guaiamuns são apreendidos durante operação na Bahia",
        "resumo": "Atualização via Radar Consuldente.",
        "cat": "FEIRA DE SANTANA",
        "fonte": "G1 Feira",
        "data": "19:14",
        "url": "https://g1.globo.com/ba/feira-de-santana-regiao/noticia/2026/04/20/caranguejos-e-guaiamuns-sao-apreendidos-durante-operacao-na-bahia.ghtml",
        "img": "https://picsum.photos/seed/844/800/400"
    },
    {
        "titulo": "Homem é arremessado de carro e morre após colisão no interior da Bahia; veículo caiu em ribance",
        "resumo": "Atualização via Radar Consuldente.",
        "cat": "FEIRA DE SANTANA",
        "fonte": "G1 Feira",
        "data": "19:14",
        "url": "https://g1.globo.com/ba/feira-de-santana-regiao/noticia/2026/04/20/homem-e-arremessado-de-carro-e-morre-apos-colisao-em-ipira.ghtml",
        "img": "https://picsum.photos/seed/782/800/400"
    },
    {
        "titulo": "CRO-BA participa de reunião com gestão municipal de Ipiaú em defesa da valorização da Odontolog",
        "resumo": "Atualização via Radar Consuldente.",
        "cat": "ODONTOLOGIA",
        "fonte": "CRO-BA",
        "data": "19:14",
        "url": "https://croba.org.br/cro-ba-participa-de-reuniao-com-gestao-municipal-de-ipiau-em-defesa-da-valorizacao-da-odontologia/",
        "img": "https://picsum.photos/seed/176/800/400"
    },
    {
        "titulo": "Circuito CRO-BA – Ética em Movimento reúne profissionais e estudantes em Senhor do Bonfim",
        "resumo": "Atualização via Radar Consuldente.",
        "cat": "ODONTOLOGIA",
        "fonte": "CRO-BA",
        "data": "19:14",
        "url": "https://croba.org.br/circuito-cro-ba-etica-em-movimento-reune-profissionais-e-estudantes-em-senhor-do-bonfim/",
        "img": "https://picsum.photos/seed/540/800/400"
    },
    {
        "titulo": "Copa do Mundo 2026 incentiva consumo de produtos da Seleção Brasileira",
        "resumo": "Portal Oficial - Clique para ler mais.",
        "cat": "FEIRA DE SANTANA",
        "fonte": "Acorda Cidade",
        "data": "19:14",
        "url": "https://www.acordacidade.com.br/brasil/copa-do-mundo-2026-incentiva-consumo-de-produtos-da-selecao-brasileira/",
        "img": "https://picsum.photos/seed/637/800/400"
    },
    {
        "titulo": "Menina de 12 anos morre após ter cabelo sugado pelo ralo em piscina",
        "resumo": "Portal Oficial - Clique para ler mais.",
        "cat": "FEIRA DE SANTANA",
        "fonte": "Folha do Estado",
        "data": "19:14",
        "url": "https://www.jornalfolhadoestado.com/brasil/menina-de-12-anos-morre-apos-ter-cabelo-sugado-pelo-ralo-em-piscina/",
        "img": "https://picsum.photos/seed/533/800/400"
    },
    {
        "titulo": "Adolescente com suspeita de embriaguez colide carro contra portão do Centro de Convenções em Fe",
        "resumo": "Portal Oficial - Clique para ler mais.",
        "cat": "FEIRA DE SANTANA",
        "fonte": "Acorda Cidade",
        "data": "19:14",
        "url": "https://www.acordacidade.com.br/policia/adolescente-com-suspeita-de-embriaguez-colide-carro-contra-portao-do-centro-de-convencoes-em-feira-de-santana/",
        "img": "https://picsum.photos/seed/452/800/400"
    },
    {
        "titulo": "Cirurgia Estética Orofacial é oficialmente regulamentada",
        "resumo": "Portal Oficial - Clique para ler mais.",
        "cat": "ODONTOLOGIA",
        "fonte": "CFO Federal",
        "data": "19:13",
        "url": "https://website.cfo.org.br/cirurgia-estetica-orofacial-e-oficialmente-regulamentada/",
        "img": "https://website.cfo.org.br/wp-content/uploads/2026/03/DSC0432-scaled.jpg"
    },
    {
        "titulo": "Mãe de Henry Borel, Monique Medeiros se entrega à polícia",
        "resumo": "Portal Oficial - Clique para ler mais.",
        "cat": "FEIRA DE SANTANA",
        "fonte": "Folha do Estado",
        "data": "19:14",
        "url": "https://www.jornalfolhadoestado.com/brasil/mae-de-henry-borel-monique-medeiros-se-entrega-a-policia/",
        "img": "https://picsum.photos/seed/621/800/400"
    },
    {
        "titulo": "ABO Bahia sedia Jornada Estadual sobre Hanseníase: “Conhecer e Cuidar, de Janeiro a Janeiro”",
        "resumo": "Portal Oficial - Clique para ler mais.",
        "cat": "ODONTOLOGIA",
        "fonte": "ABO-BA",
        "data": "19:14",
        "url": "https://abo-ba.org.br/abo-bahia-sedia-jornada-estadual-sobre-hanseniase-conhecer-e-cuidar-de-janeiro-a-janeiro/",
        "img": "https://abo-ba.org.br/wp-content/uploads/2025/05/capas-abo-.png"
    },
    {
        "titulo": "CRO-BA participa de ato público em Brasília em defesa da PEC 2/2026 e dialoga com o senador Ang",
        "resumo": "Atualização via Radar Consuldente.",
        "cat": "ODONTOLOGIA",
        "fonte": "CRO-BA",
        "data": "19:14",
        "url": "https://croba.org.br/cro-ba-participa-de-ato-publico-em-brasilia-em-defesa-da-pec-2-2026-e-dialoga-com-o-senador-angelo-coronel/",
        "img": "https://picsum.photos/seed/82/800/400"
    },
    {
        "titulo": "Presidente do CFO prestigia posse da nova diretoria do CRO-DF",
        "resumo": "Portal Oficial - Clique para ler mais.",
        "cat": "ODONTOLOGIA",
        "fonte": "CFO Federal",
        "data": "19:14",
        "url": "https://website.cfo.org.br/presidente-do-cfo-prestigia-posse-da-nova-diretoria-do-cro-df/",
        "img": "https://website.cfo.org.br/wp-content/uploads/2026/03/DSCF3872-scaled.jpg"
    },
    {
        "titulo": "A nova era da harmonização orofacial começa com conhecimento de verdade e você pode fazer parte",
        "resumo": "Portal Oficial - Clique para ler mais.",
        "cat": "ODONTOLOGIA",
        "fonte": "ABO-BA",
        "data": "19:14",
        "url": "https://abo-ba.org.br/a-nova-era-da-harmonizacao-orofacial-comeca-com-conhecimento-de-verdade-e-voce-pode-fazer-parte/",
        "img": "https://abo-ba.org.br/wp-content/uploads/2025/05/Black-and-Gold-Illustrated-Webinar-Event-Instagram-Post-1920-x-1080-px.png"
    },
    {
        "titulo": "Fluminense de Feira anuncia Edu Silva como novo técnico para a Série B do Baianão",
        "resumo": "Portal Oficial - Clique para ler mais.",
        "cat": "FEIRA DE SANTANA",
        "fonte": "Acorda Cidade",
        "data": "19:14",
        "url": "https://www.acordacidade.com.br/esportes/futebol/fluminense-de-feira-anuncia-edu-silva-como-novo-tecnico-para-a-serie-b-do-baianao/",
        "img": "https://picsum.photos/seed/426/800/400"
    },
    {
        "titulo": "Justiça determina criação de Centro de Zoonoses e abrigo de animais em Santo Antônio de Jesus",
        "resumo": "Atualização via Radar Consuldente.",
        "cat": "FEIRA DE SANTANA",
        "fonte": "G1 Feira",
        "data": "19:14",
        "url": "https://g1.globo.com/ba/feira-de-santana-regiao/noticia/2026/04/18/justica-determina-criacao-de-centro-de-zoonoses-e-abrigo-de-animais-em-santo-antonio-de-jesus.ghtml",
        "img": "https://picsum.photos/seed/461/800/400"
    },
    {
        "titulo": "Presidente do CFO prestigia posse da nova diretoria do CRO-GO",
        "resumo": "Portal Oficial - Clique para ler mais.",
        "cat": "ODONTOLOGIA",
        "fonte": "CFO Federal",
        "data": "19:13",
        "url": "https://website.cfo.org.br/presidente-do-cfo-prestigia-posse-da-nova-diretoria-do-cro-go/",
        "img": "https://website.cfo.org.br/wp-content/uploads/2026/03/CAR08361-scaled.jpg"
    },
    {
        "titulo": "Clube de Benefícios",
        "resumo": "Portal Oficial - Clique para ler mais.",
        "cat": "ODONTOLOGIA",
        "fonte": "CFO Federal",
        "data": "19:13",
        "url": "https://website.cfo.org.br/clube-beneficios",
        "img": "https://website.cfo.org.br/wp-content/uploads/2026/03/arte-beneficios-scaled.png"
    },
    {
        "titulo": "Assista aos telejornais da TV Subaé",
        "resumo": "Atualização via Radar Consuldente.",
        "cat": "FEIRA DE SANTANA",
        "fonte": "G1 Feira",
        "data": "19:14",
        "url": "https://g1.globo.com/ba/feira-de-santana-regiao/ao-vivo/assista-aos-telejornais-da-tv-subae.ghtml",
        "img": "https://picsum.photos/seed/321/800/400"
    },
    {
        "titulo": "Jornalista morre aos 33 anos após infarto fulminante em Feira de Santana",
        "resumo": "Atualização via Radar Consuldente.",
        "cat": "FEIRA DE SANTANA",
        "fonte": "G1 Feira",
        "data": "19:14",
        "url": "https://g1.globo.com/ba/feira-de-santana-regiao/noticia/2026/04/20/jornalista-morre-apos-infarto-fulminante-em-feira-de-santana.ghtml",
        "img": "https://picsum.photos/seed/793/800/400"
    },
    {
        "titulo": "Mensagens da luz",
        "resumo": "Portal Oficial - Clique para ler mais.",
        "cat": "FEIRA DE SANTANA",
        "fonte": "Acorda Cidade",
        "data": "19:14",
        "url": "https://www.acordacidade.com.br/dom-itamar-vian/mensagens-da-luz/",
        "img": "https://picsum.photos/seed/148/800/400"
    },
    {
        "titulo": "Operação captura mais três integrantes de facção baiana no Rio de Janeiro",
        "resumo": "Portal Oficial - Clique para ler mais.",
        "cat": "FEIRA DE SANTANA",
        "fonte": "Folha do Estado",
        "data": "19:14",
        "url": "https://www.jornalfolhadoestado.com/policia/operacao-captura-mais-tres-integrantes-de-faccao-baiana-no-rio-de-janeiro/",
        "img": "https://picsum.photos/seed/661/800/400"
    },
    {
        "titulo": "CRO-BA acompanha, em Brasília, aprovação do relatório do PL 1365/2022 na CAE",
        "resumo": "Atualização via Radar Consuldente.",
        "cat": "ODONTOLOGIA",
        "fonte": "CRO-BA",
        "data": "19:14",
        "url": "https://croba.org.br/cro-ba-acompanha-em-brasilia-aprovacao-do-relatorio-do-pl-1365-2022-na-cae/",
        "img": "https://picsum.photos/seed/914/800/400"
    },
    {
        "titulo": "Café &#038; Prosa promove reflexão sobre autocuidado na ABO-BA",
        "resumo": "Portal Oficial - Clique para ler mais.",
        "cat": "ODONTOLOGIA",
        "fonte": "ABO-BA",
        "data": "19:14",
        "url": "https://abo-ba.org.br/cafe-prosa-promove-reflexao-sobre-autocuidado-na-abo-ba/",
        "img": "https://abo-ba.org.br/wp-content/uploads/2025/07/1.png"
    },
    {
        "titulo": "Prefeitura e Senai oferecem curso gratuito de costura industrial com bolsa de R$ 500 em distrit",
        "resumo": "Atualização via Radar Consuldente.",
        "cat": "FEIRA DE SANTANA",
        "fonte": "G1 Feira",
        "data": "19:14",
        "url": "https://g1.globo.com/ba/feira-de-santana-regiao/noticia/2026/04/20/curso-gratuito-em-feira-de-santana.ghtml",
        "img": "https://picsum.photos/seed/704/800/400"
    },
    {
        "titulo": "Nova gestão do CFO homenageia liderança feminina e reafirma compromisso com a equidade no Siste",
        "resumo": "Portal Oficial - Clique para ler mais.",
        "cat": "ODONTOLOGIA",
        "fonte": "CFO Federal",
        "data": "19:14",
        "url": "https://website.cfo.org.br/nova-gestao-do-cfo-homenageia-lideranca-feminina-e-reafirma-compromisso-com-a-equidade-no-sistema-conselhos-de-odontologia/",
        "img": "https://website.cfo.org.br/wp-content/uploads/2026/03/Presidentes-dos-Conselhos-Regionais-de-Odontologia.jpeg"
    },
    {
        "titulo": "São João da ABO-BA celebra tradição, alegria e união da classe odontológica",
        "resumo": "Portal Oficial - Clique para ler mais.",
        "cat": "ODONTOLOGIA",
        "fonte": "ABO-BA",
        "data": "19:14",
        "url": "https://abo-ba.org.br/sao-joao-da-abo-ba-celebra-tradicao-alegria-e-uniao-da-classe-odontologica/",
        "img": "https://abo-ba.org.br/wp-content/uploads/2025/07/2.png"
    },
    {
        "titulo": "Neurocirurgia avança e amplia chances de sobrevivência",
        "resumo": "Portal Oficial - Clique para ler mais.",
        "cat": "FEIRA DE SANTANA",
        "fonte": "Acorda Cidade",
        "data": "19:14",
        "url": "https://www.acordacidade.com.br/saude/neurocirurgia-avanca-e-amplia-chances-de-sobrevivencia/",
        "img": "https://picsum.photos/seed/140/800/400"
    },
    {
        "titulo": "Adolescente colide veículo no portão do Centro de Convenções, em Feira",
        "resumo": "Portal Oficial - Clique para ler mais.",
        "cat": "FEIRA DE SANTANA",
        "fonte": "Folha do Estado",
        "data": "19:14",
        "url": "https://www.jornalfolhadoestado.com/policia/adolescente-colide-veiculo-no-portao-do-centro-de-convencoes-em-feira/",
        "img": "https://picsum.photos/seed/219/800/400"
    },
    {
        "titulo": "CRO-BA participa da 1ª cerimônia oficial de assinatura do Manifesto ESG / ODS",
        "resumo": "Atualização via Radar Consuldente.",
        "cat": "ODONTOLOGIA",
        "fonte": "CRO-BA",
        "data": "19:14",
        "url": "https://croba.org.br/cro-ba-participa-da-1a-cerimonia-oficial-de-assinatura-do-manifesto-esg-ods/",
        "img": "https://picsum.photos/seed/938/800/400"
    }
]